aditi/__init__.py
aditi/__main__.py
aditi/cli.py
aditi/cli_prototype.py
aditi/config.py
aditi/git.py
aditi/processor.py
aditi/py.typed
aditi/scanner.py
aditi/vale_container.py
aditi/vale_parser.py
aditi/commands/__init__.py
aditi/commands/check.py
aditi/commands/fix.py
aditi/commands/init.py
aditi/commands/journey.py
aditi/commands/vale.py
aditi/rules/__init__.py
aditi/rules/admonition_title.py
aditi/rules/attribute_reference.py
aditi/rules/author_line.py
aditi/rules/base.py
aditi/rules/block_title.py
aditi/rules/conditional_code.py
aditi/rules/content_type.py
aditi/rules/cross_reference.py
aditi/rules/discrete_heading.py
aditi/rules/entity_reference.py
aditi/rules/equation_formula.py
aditi/rules/example_block.py
aditi/rules/include_directive.py
aditi/rules/line_break.py
aditi/rules/link_attribute.py
aditi/rules/nested_section.py
aditi/rules/page_break.py
aditi/rules/registry.py
aditi/rules/related_links.py
aditi/rules/short_description.py
aditi/rules/sidebar_block.py
aditi/rules/table_footer.py
aditi/rules/tag_directive.py
aditi/rules/task_duplicate.py
aditi/rules/task_example.py
aditi/rules/task_section.py
aditi/rules/task_step.py
aditi/rules/task_title.py
aditi/rules/thematic_break.py
aditi/vale/vale_config_template.ini
aditi-0.1.9.dist-info/licenses/LICENSE
aditi-0.1.9.dist-info/METADATA
aditi-0.1.9.dist-info/WHEEL
aditi-0.1.9.dist-info/entry_points.txt
aditi-0.1.9.dist-info/top_level.txt
aditi-0.1.9.dist-info/RECORD
