Metadata-Version: 2.4
Name: aditi
Version: 0.1.9
Summary: A CLI tool to prepare AsciiDoc files for migration to DITA
Author-email: Rolfe Dlugy-Hegwer <rolfedh@github.com>
Maintainer-email: Rolfe Dlugy-Hegwer <rolfedh@github.com>
License-Expression: MIT
Project-URL: Homepage, https://github.com/rolfedh/aditi
Project-URL: Documentation, https://rolfedh.github.io/aditi/
Project-URL: Repository, https://github.com/rolfedh/aditi.git
Project-URL: Issues, https://github.com/rolfedh/aditi/issues
Keywords: asciidoc,dita,documentation,migration,vale,linter
Classifier: Development Status :: 3 - Alpha
Classifier: Intended Audience :: Developers
Classifier: Topic :: Software Development :: Documentation
Classifier: Programming Language :: Python :: 3
Classifier: Programming Language :: Python :: 3.11
Classifier: Programming Language :: Python :: 3.12
Classifier: Programming Language :: Python :: 3.13
Classifier: Operating System :: OS Independent
Classifier: Environment :: Console
Requires-Python: >=3.11
License-File: LICENSE
Requires-Dist: typer>=0.9.0
Requires-Dist: rich>=13.7.0
Requires-Dist: pydantic>=2.5.0
Requires-Dist: pydantic-settings>=2.1.0
Requires-Dist: questionary>=2.0.0
Provides-Extra: dev
Requires-Dist: pytest>=7.4.0; extra == "dev"
Requires-Dist: pytest-cov>=4.1.0; extra == "dev"
Requires-Dist: pytest-mock>=3.12.0; extra == "dev"
Requires-Dist: pyyaml>=6.0.0; extra == "dev"
Requires-Dist: mypy>=1.8.0; extra == "dev"
Requires-Dist: ruff>=0.1.9; extra == "dev"
Requires-Dist: black>=23.12.0; extra == "dev"
Requires-Dist: pre-commit>=3.6.0; extra == "dev"
Dynamic: license-file
